marimo_jupyter_extension/__init__.py
marimo_jupyter_extension/config.py
marimo_jupyter_extension/convert.py
marimo_jupyter_extension/executable.py
marimo_jupyter_extension/exporter.py
marimo_jupyter_extension/handlers.py
marimo_jupyter_extension/icon.svg
marimo_jupyter_extension/etc/jupyter_server_config.d/marimo_jupyter_extension.json
marimo_jupyter_extension/labextension/package.json
marimo_jupyter_extension/labextension/schemas/@marimo-team/jupyter-extension/package.json.orig
marimo_jupyter_extension/labextension/schemas/@marimo-team/jupyter-extension/plugin.json
marimo_jupyter_extension/labextension/static/510.5a6289689ce7a0453fc4.js
marimo_jupyter_extension/labextension/static/remoteEntry.705371d091b7d314fd9e.js
marimo_jupyter_extension/labextension/static/style.js
marimo_jupyter_extension/labextension/static/third-party-licenses.json
marimo_jupyter_extension-0.1.0.data/data/etc/jupyter/jupyter_server_config.d/marimo_jupyter_extension.json
marimo_jupyter_extension-0.1.0.data/data/share/jupyter/labextensions/@marimo-team/jupyter-extension/package.json
marimo_jupyter_extension-0.1.0.data/data/share/jupyter/labextensions/@marimo-team/jupyter-extension/schemas/@marimo-team/jupyter-extension/package.json.orig
marimo_jupyter_extension-0.1.0.data/data/share/jupyter/labextensions/@marimo-team/jupyter-extension/schemas/@marimo-team/jupyter-extension/plugin.json
marimo_jupyter_extension-0.1.0.data/data/share/jupyter/labextensions/@marimo-team/jupyter-extension/static/510.5a6289689ce7a0453fc4.js
marimo_jupyter_extension-0.1.0.data/data/share/jupyter/labextensions/@marimo-team/jupyter-extension/static/remoteEntry.705371d091b7d314fd9e.js
marimo_jupyter_extension-0.1.0.data/data/share/jupyter/labextensions/@marimo-team/jupyter-extension/static/style.js
marimo_jupyter_extension-0.1.0.data/data/share/jupyter/labextensions/@marimo-team/jupyter-extension/static/third-party-licenses.json
marimo_jupyter_extension-0.1.0.dist-info/METADATA
marimo_jupyter_extension-0.1.0.dist-info/WHEEL
marimo_jupyter_extension-0.1.0.dist-info/entry_points.txt
marimo_jupyter_extension-0.1.0.dist-info/licenses/LICENSE
marimo_jupyter_extension-0.1.0.dist-info/licenses/NOTICE
marimo_jupyter_extension-0.1.0.dist-info/RECORD
