Metadata-Version: 2.4
Name: marimo-jupyter-extension
Version: 0.1.0
Summary: Jupyter extension to proxy marimo with JupyterLab integration
Project-URL: Homepage, https://github.com/marimo-team/marimo-jupyter-extension
Project-URL: Documentation, https://marimo-team.github.io/marimo-jupyter-extension/
Project-URL: Repository, https://github.com/marimo-team/marimo-jupyter-extension
Project-URL: Issues, https://github.com/marimo-team/marimo-jupyter-extension/issues
Author: Marimo Team, Jiang Yio
License-Expression: Apache-2.0
License-File: LICENSE
License-File: NOTICE
Classifier: Development Status :: 4 - Beta
Classifier: Framework :: Jupyter
Classifier: Framework :: Jupyter :: JupyterLab
Classifier: Framework :: Jupyter :: JupyterLab :: 4
Classifier: Framework :: Jupyter :: JupyterLab :: Extensions
Classifier: Framework :: Jupyter :: JupyterLab :: Extensions :: Prebuilt
Classifier: Intended Audience :: Developers
Classifier: Intended Audience :: Science/Research
Classifier: Programming Language :: Python :: 3
Classifier: Programming Language :: Python :: 3.10
Classifier: Programming Language :: Python :: 3.11
Classifier: Programming Language :: Python :: 3.12
Classifier: Programming Language :: Python :: 3.13
Requires-Python: >=3.10
Requires-Dist: jupyter-server-proxy
Requires-Dist: nbconvert>=7.0
Requires-Dist: pyzmq>=27.1.0
Requires-Dist: traitlets>=5.0
Requires-Dist: uv>=0.4
Provides-Extra: dev
Requires-Dist: pytest-cov>=4.0; extra == 'dev'
Requires-Dist: pytest>=7.0; extra == 'dev'
Requires-Dist: ruff>=0.8.0; extra == 'dev'
Provides-Extra: docs
Requires-Dist: mkdocs-material>=9.0; extra == 'docs'
Requires-Dist: mkdocs>=1.5; extra == 'docs'
